src/__init__.py
src/cheermeup.py
cheermeup-1.0.1.dist-info/LICENSE
cheermeup-1.0.1.dist-info/METADATA
cheermeup-1.0.1.dist-info/WHEEL
cheermeup-1.0.1.dist-info/entry_points.txt
cheermeup-1.0.1.dist-info/top_level.txt
cheermeup-1.0.1.dist-info/RECORD
