Metadata-Version: 2.1
Name: cheermeup
Version: 1.0.1
Summary: Command line program to play random animal videos.
Home-page: https://github.com/andohuman/cheermeup
Author: Gautham Venkataraman
Author-email: gauthsvenkat@gmail.com
Maintainer: Gautham Venkataraman
Maintainer-email: gauthsvenkat@gmail.com
License: UNKNOWN
Download-URL: https://github.com/andohuman/cheermeup/archive/refs/tags/v1.0.1.tar.gz
Platform: UNKNOWN
License-File: LICENSE
Requires-Dist: opencv-python
Requires-Dist: praw
Requires-Dist: appdirs
